{
    "ID": "chat-01",
    "ChatName": "แก๊งเด็กหลังห้อง นัดเที่ยว",
    "Icon": [
        "Image/Story1/profileJ",
        "Image/Story1/profileP"
    ],
    "DataDetail": [{
        "ID": "chat-01",
        "OnwerName": "my",
        "Icon": "",
        "ChatType": "Time",
        "DelayTime": 0,
        "Content": "7 เม.ย. 2024 10:20",
        "PostImage": "",
        "LinkToPageName": ""
    },

        {
            "ID": "chat-01",
            "OnwerName": "จอม",
            "Icon": "Image/Story1/profileJ",
            "ChatType": "Normal",
            "DelayTime": 3,
            "Content": "หยุดยาวนี้ไปเที่ยวกันไหม",
            "PostImage": "",
            "LinkToPageName": ""
        },
        
        {
            "ID": "chat-01",
            "OnwerName": "ภู",
            "Icon": "Image/Story1/profileP",
            "ChatType": "Normal",
            "DelayTime": 3,
            "Content": "ที่ไหน",
            "PostImage": "",
            "LinkToPageName": ""
        },
        {
            "ID": "chat-01",
            "OnwerName": "จอม",
            "Icon": "Image/Story1/profileJ",
            "ChatType": "Normal",
            "DelayTime": 3,
            "Content": "ยังไม่รู้หาเพื่อน มาถามก่อน\nว่ามีใครไปไหม",
            "PostImage": "",
            "LinkToPageName": ""
        },
        {
            "ID": "chat-01",
            "OnwerName": "ภู",
            "Icon": "Image/Story1/profileP",
            "ChatType": "Normal",
            "DelayTime": 3,
            "Content": "เรื่องเที่ยวต้องถามคนนี้เลย {Player} ไป\nไหนดี",
            "PostImage": "",
            "LinkToPageName": ""
        },
        {
            "ID": "chat-01",
            "OnwerName": "my",
            "Icon": "",
            "ChatType": "Normal",
            "DelayTime": 2,
            "Content": "ไป{0}ไหม",
            "Choice": [
                {
                    "ID": "001",
                    "Path": "เขาใหญ่",
                    "LinkType": "chat",
                    "FileName": "Route1/story1-2"
                },
                {
                    "ID": "001",
                    "Path": "เกาะล้าน",
                    "LinkType": "chat",
                    "FileName": "Route1/story1-2"
                },
                {
                    "ID": "001",
                    "Path": "กาญจนบุรี",
                    "LinkType": "chat",
                    "FileName": "Route1/story1-2"
                }
            ],
            "PostImage": "",
            "LinkToPageName": "Route1/RouteN/story1-20-1",
            "LinkType": "",
            "FileName": ""
        }
    ]
}